djackal/__init__.py
djackal/apps.py
djackal/exceptions.py
djackal/expressions.py
djackal/fields/__init__.py
djackal/fields/json_field.py
djackal/initializer.py
djackal/loaders.py
djackal/management/__init__.py
djackal/management/commands/__init__.py
djackal/management/commands/init.py
djackal/model_mixins/__init__.py
djackal/model_mixins/extra_mixin.py
djackal/pagination.py
djackal/permissions.py
djackal/query_filter.py
djackal/serializers.py
djackal/settings.py
djackal/shortcuts.py
djackal/storage/__init__.py
djackal/storage/apps.py
djackal/storage/migrations/0001_initial.py
djackal/storage/migrations/__init__.py
djackal/storage/models.py
djackal/tests.py
djackal/utils.py
djackal/views/__init__.py
djackal/views/base.py
djackal/views/generics.py
djackal/views/handler.py
djackal/views/mixins.py
djackal-0.7.0.dist-info/LICENSE
djackal-0.7.0.dist-info/METADATA
djackal-0.7.0.dist-info/WHEEL
djackal-0.7.0.dist-info/RECORD
