Metadata-Version: 2.1
Name: djackal
Version: 0.7.0
Summary: extension of Django REST Framework
Home-page: https://github.com/jrog612/djackal
License: MIT
Author: jrog
Author-email: jrog612@gmail.com
Requires-Python: >=3.8,<4.0
Classifier: License :: OSI Approved :: MIT License
Classifier: Programming Language :: Python :: 3
Classifier: Programming Language :: Python :: 3.8
Classifier: Programming Language :: Python :: 3.9
Classifier: Programming Language :: Python :: 3.10
Classifier: Programming Language :: Python :: 3.11
Classifier: Programming Language :: Python :: 3.12
Requires-Dist: djangorestframework (>=3.0.0,<4.0.0)
Requires-Dist: puty (>=0.0,<0.1)
Project-URL: Repository, https://github.com/jrog612/djackal
